CONTRIBUTORS.txt
LICENSE.txt
MANIFEST.in
README.rst
setup.py
django_kit/__init__.py
django_kit.egg-info/PKG-INFO
django_kit.egg-info/SOURCES.txt
django_kit.egg-info/dependency_links.txt
django_kit.egg-info/not-zip-safe
django_kit.egg-info/top_level.txt